<Settings>
    <Setting Id="ch" Label="Chapter Splits" State="false">
		<Setting Id="ActWorld_2_P" Label="Finish Chapter 1" State="false"/>
		<Setting Id="ActWorld_3_P" Label="Finish Chapter 2" State="false"/>
		<Setting Id="ActWorld_4_P" Label="Finish Chapter 3" State="false"/>
		<Setting Id="ActWorld_5_P" Label="Finish Chapter 4" State="false"/>
		<Setting Id="MainMenu" Label="Finish Chapter 5 " State="false"/>
	</Setting>
	<Setting Id="itm" Label="Item Splits" State="false">
		<Setting Id="ch1" Label="Chapter 1" State="false">
			<Setting Id="[+] ID_DercetoLaundryKey (!)" Label="Pick up Housekeeper's Key" State="false"/>
			<Setting Id="[+] ID_DercetoPiazzaKey (!)" Label="Pick up Piazza Key" State="false"/>
			<Setting Id="[+] ID_Derceto_MasterPuzzlePiece_AW1_Tutorial01 (!)" Label="Painted Tile" State="false"/>
			<Setting Id="[+] ID_BatistesKeyChain (!)" Label="Batiste's Key" State="false"/>
			<Setting Id="[+] ID_Talisman (!)" Label="Talisman" State="false"/>
		</Setting>
		<Setting Id="ch2" Label="Chapter 2" State="false">
			<Setting Id="[+] ID_DercetoPerosiKey (!)" Label="Room Key #6" State="false"/>
			<Setting Id="[+] ID_BoltCutter (!)" Label="Bolt Cutters" State="false"/>
			<Setting Id="[+] ID_Derceto_HosePiece (!)" Label="Water Hose" State="false"/>
			<Setting Id="[+] ID_Derceto_MasterPuzzlePiece_AW2_OilRig01 (!)" Label="Clock Broken Plate" State="false"/>
			<Setting Id="[+] ID_Derceto_MasterPuzzlePiece_AW2_OilRig02 (!)" Label="Clock Broken Plate 2" State="false"/>
			<Setting Id="[+] ID_OilRig_BridgePart (!)" Label="Bridge Lever" State="false"/>
			<Setting Id="[+] ID_OilRig_OilyRag (!)" Label="Tough Cloth" State="false"/>
			<Setting Id="[+] ID_Derceto_PaletteKnife (!)" Label="Palette Knife" State="false"/>
			<Setting Id="[+] ID_WineCellarKey (!)" Label="Cellar Key" State="false"/>
			<Setting Id="[+] ID_Derceto_MasterPuzzlePiece_AW2_Cemetery02 (!)" Label="Boiler Broken Plate" State="false"/>
			<Setting Id="[+] ID_Derceto_BreakerLever (!)" Label="Switch" State="false"/>
			<Setting Id="[+] ID_Derceto_BoilerHandle (!)" Label="Valve Handle" State="false"/>
			<Setting Id="[+] ID_Derceto_MasterPuzzlePiece_AW2_Cemetery01 (!)" Label="Boiler Broken Plate 2" State="false"/>
			<Setting Id="[+] ID_Cemetery_Medallion02 (!)" Label="The Blessing" State="false"/>
			<Setting Id="[+] ID_Cemetery_Medallion01 (!)" Label="The Omen" State="false"/>
			<Setting Id="[+] ID_Cemetery_Medallion03 (!)" Label="The Sacrifice" State="false"/>
			<Setting Id="[+] ID_MyEverything (!)" Label="My Everything" State="false"/>sh
			<Setting Id="[+] ID_Derceto_TelescopeLens (!)" Label="Barlow Lens" State="false"/>
		</Setting>
		<Setting Id="ch3" Label="Chapter 3" State="false">
			<Setting Id="[+] ID_Taroella_ConventLibraryKey (!)" Label="The Key of Hubertus" State="false"/>
			<Setting Id="[+] ID_TheMaccabean (!)" Label="Matchbook" State="false"/>
			<Setting Id="[+] ID_GallatinStreetCraneKey (!)" Label="Stevedore's Key" State="false"/>
			<Setting Id="[+] ID_GallatinCargoManifesto (!)" Label="Cargo Manifest" State="false"/>
			<Setting Id="[+] ID_DSS_Rope (!)" Label="Rope" State="false"/>
			<Setting Id="[+] ID_DSS_Mirror03 (!)" Label="The Horizon" State="false"/>
			<Setting Id="[+] ID_DSS_Mirror01 (!)" Label="The Star" State="false"/>
			<Setting Id="[+] ID_DSS_Mirror02 (!)" Label="The Underworld" State="false"/>
		</Setting>
		<Setting Id="ch4" Label="Chapter 4" State="false">
			<Setting Id="[+] ID_DercetoOfficeKey (!)" Label="Dr. Gray's Office Key" State="false"/>
			<Setting Id="[+] ID_DercetoSpiralStairHallKey (!)" Label="Stairwell Key" State="false"/>
			<Setting Id="[+] ID_DercetoVestibuleF1Key (!)" Label="1st Floor Hall Key" State="false"/>
			<Setting Id="[+] ID_Derceto_Picayune (!)" Label="Picayune" State="false"/>
			<Setting Id="[+] ID_Derceto_XRayFilm01 (!)" Label="Radiograph #1" State="false"/>
			<Setting Id="[+] ID_Derceto_XRayFilm02 (!)" Label="Radiograph #2" State="false"/>
			<Setting Id="[+] ID_Derceto_ClayStatuettePiece (!)" Label="Jeremy's Darkness" State="false"/>
			<Setting Id="[+] ID_Steamboat_FuelCanEmpty (!)" Label="Empty Gas Can" State="false"/>
			<Setting Id="[+] ID_Steamboat_FuelCanFull (!)" Label="Filled Gas Can" State="false"/>
			<Setting Id="[+] ID_Derceto_GracesDrawing2 (!)" Label="The Missing Picture" State="false"/>
			<Setting Id="[+] ID_FrenchQuarterRevisitDeskKey (!)" Label="Writing Desk Key" State="false"/>
			<Setting Id="[+] ID_FQ_Hotel2ndClue (!)" Label="Hotel Bill" State="false"/>
			<Setting Id="[+] ID_FQ_Hotel1stClue (!)" Label="Business Card" State="false"/>
			<Setting Id="[+] ID_Derceto_AW4_FalseBookKey (!)" Label="False Book" State="false"/>
			<Setting Id="[+] ID_AW4_GraysWardrobeKey (!)" Label="Furniture Key" State="false"/>
		</Setting>
	</Setting>
	<Setting Id="cut" Label="Cutscenes" State="false">
		<Setting Id="Edw" Label="Edward" State="false">
			<Setting Id="Edw1" Label="Chapter 1" State="false">
				<Setting Id="cin_020_edw_lobby_scene" Label="Open the Door For Emily" State="false"/>
				<Setting Id="cin_030_edw_portrait_of_a_dark_man" Label="Find Portrait of Jeremy" State="false"/>
				<Setting Id="cin_040_edw_johnny_the_conqueror" Label="Meet Batiste" State="false"/>
				<Setting Id="cin_050_edw_whats_up_doc" Label="Meet Dr. Gray" State="false"/>
			</Setting>
			<Setting Id="Edw2" Label="Chapter 2" State="false">
				<Setting Id="cin_110_edw_you_and_me_buddy" Label="Meet Drunk Man" State="false"/>
				<Setting Id="cin_082_edw_falling_out" Label="Fall Out of Boathouse" State="false"/>
				<Setting Id="cin_084_edw_zipline" Label="Use the Zipline" State="false"/>
				<Setting Id="cin_080_edw_tomb_raiding" Label="Meet Lottie In the Tomb" State="false"/>
				<Setting Id="cin_100_edw_keeper_of_secrets" Label="Meet Grace" State="false"/>
				<Setting Id="cin_070_edw_finding_jeremy" Label="Meet Jeremy" State="false"/>
				<Setting Id="cin_090_edw_bearcat" Label="Meet Ruth" State="false"/>
			</Setting>
			<Setting Id="Edw3" Label="Chapter 3" State="false">
				<Setting Id="LS_DarkmanIntro_Edw1" Label="Meet the Darkman" State="false"/>
				<Setting Id="cin_150_edw_the_maccabean" Label="Meet Ruth In the Bar" State="false"/>
				<Setting Id="cin_160_edw_the_black_pharaoh" Label="The Black Pharaoh" State="false"/>
				<Setting Id="cin_165_edw_rappel" Label="Rappel" State="false"/>
				<Setting Id="cin_170_edw_bats_in_the_belfry_PT1" Label="Bats in the Belfry" State="false"/>
			</Setting>
			<Setting Id="Edw4" Label="Chapter 4" State="false">
				<Setting Id="cin_210_edw_overhearing_the_orderlies" Label="Overhearing The Orderlies" State="false"/>
				<Setting Id="cin_220_edw_babysitting" Label="Babysitting" State="false"/>
				<Setting Id="cin_180_edw_hes_all_wet" Label="He's All Wet" State="false"/>
				<Setting Id="cin_190_edw_pearl_river_bridge" Label="Pearl River Bridge" State="false"/>
				<Setting Id="cin_200_edw_into_the_abyss" Label="Into The Abyss" State="false"/>
				<Setting Id="S_ObservatoryCollapse_Edw" Label="Observatory Collapse" State="false"/>
				<Setting Id="LSE_Edw_JacobStab" Label="Jacob Stab" State="false"/>
			</Setting>
			<Setting Id="Edw5" Label="Chapter 5" State="false">
				<Setting Id="cin_265_edw_chaos" Label="Chaos" State="false"/>
				<Setting Id="LS_ShubIntro" Label="Boss Fight Start" State="false"/>
				<Setting Id="LS_EndTransition_Edw" Label="Boss Fight End" State="false"/>
			</Setting>
		</Setting>
		<Setting Id="Emi" Label="Emily" State="false">
			<Setting Id="Emi1" Label="Chapter 1" State="false">
				<Setting Id="cin_290_emi_lobby_scene" Label="Open the Door For Edward" State="false"/>
				<Setting Id="cin_300_emi_portrait_of_a_dark_man" Label="Find Portrait of Jeremy" State="false"/>
				<Setting Id="cin_310_emi_johnny_the_conqueror" Label="Meet Batiste" State="false"/>
				<Setting Id="cin_320_emi_whats_up_doc" Label="Meet Dr. Gray" State="false"/>
			</Setting>
			<Setting Id="Emi2" Label="Chapter 2" State="false">
				<Setting Id="cin_360_emi_making_friends_02" Label="Making Friends" State="false"/>
				<Setting Id="cin_352_emi_falling_out" Label="Fall Out of Boathouse" State="false"/>
				<Setting Id="cin_354_emi_zipline" Label="Use the Zipline" State="false"/>
				<Setting Id="cin_350_emi_tomb_raiding" Label="Meet Lottie In the Tomb" State="false"/>
				<Setting Id="cin_380_emi_drugstore_cowboy" Label="Drugstore Cowboy" State="false"/>
				<Setting Id="cin_340_emi_finding_jeremy" Label="Meet Jeremy" State="false"/>
				<Setting Id="cin_370_emi_grace_is_not_alright" Label="Meet Grace" State="false"/>
			</Setting>
			<Setting Id="Emi3" Label="Chapter 3" State="false">
				<Setting Id="LS_DarkmanIntro_Eml" Label="Meet the Darkman" State="false"/>
				<Setting Id="cin_420_emi_the_maccabean" Label="Meet Ruth In the Bar" State="false"/>
				<Setting Id="cin_160_edw_the_black_pharaoh" Label="The Black Pharaoh" State="false"/>
				<Setting Id="cin_165_edw_rappel" Label="Rappel" State="false"/>
				<Setting Id="cin_170_edw_bats_in_the_belfry_PT1" Label="Bats in the Belfry" State="false"/>
			</Setting>
			<Setting Id="Emi4" Label="Chapter 4" State="false">
				<Setting Id="cin_210_edw_overhearing_the_orderlies" Label="Overhearing The Orderlies" State="false"/>
				<Setting Id="cin_220_edw_babysitting" Label="Babysitting" State="false"/>
				<Setting Id="cin_180_edw_hes_all_wet" Label="He's All Wet" State="false"/>
				<Setting Id="cin_190_edw_pearl_river_bridge" Label="Pearl River Bridge" State="false"/>
				<Setting Id="cin_200_edw_into_the_abyss" Label="Into The Abyss" State="false"/>
				<Setting Id="S_ObservatoryCollapse_Edw" Label="Observatory Collapse" State="false"/>
				<Setting Id="LSE_Edw_JacobStab" Label="Jacob Stab" State="false"/>
			</Setting>
			<Setting Id="Emi5" Label="Chapter 5" State="false">
				<Setting Id="cin_265_edw_chaos" Label="Chaos" State="false"/>
				<Setting Id="LS_ShubIntro" Label="Boss Fight Start" State="false"/>
				<Setting Id="LS_EndTransition_Edw" Label="Boss Fight End" State="false"/>
			</Setting>
		</Setting>
	</Setting>
</Settings>  